frc_characterization/__init__.py
frc_characterization/__main__.py
frc_characterization/cli/__init__.py
frc_characterization/logger_analyzer/__init__.py
frc_characterization/logger_analyzer/data_analyzer.py
frc_characterization/logger_analyzer/data_logger.py
frc_characterization/logger_analyzer/templates/Robot.java.mako
frc_characterization/logger_analyzer/templates/__init__.py
frc_characterization/logger_analyzer/templates/build.gradle.mako
frc_characterization/logger_analyzer/templates/configs/ctreconfig.py
frc_characterization/logger_analyzer/templates/configs/pwfconfig.py
frc_characterization/logger_analyzer/templates/configs/simpleconfig.py
frc_characterization/logger_analyzer/templates/configs/sparkmaxconfig.py
frc_characterization/logger_gui/__init__.py
frc_characterization/newproject/__init__.py
frc_characterization/robot/__init__.py
frc_characterization/robot/project/.classpath
frc_characterization/robot/project/.project
frc_characterization/robot/project/gradlew
frc_characterization/robot/project/gradlew.bat
frc_characterization/robot/project/settings.gradle
frc_characterization/robot/project/gradle/wrapper/gradle-wrapper.jar
frc_characterization/robot/project/gradle/wrapper/gradle-wrapper.properties
frc_characterization/robot/project/src/main/java/dc/Main.java
frc_characterization/robot/project/src/main/java/dc/SimEnabler.java
frc_characterization/robot/project/vendordeps/Phoenix.json
frc_characterization/robot/project/vendordeps/REVRobotics.json
frc_characterization/robot/project/vendordeps/navx_frc.json
frc_characterization/robot/project/vendordeps/playingwithfusion2021.json
frc_characterization/utils/__init__.py
frc_characterization-2021.2.4.dist-info/LICENSE
frc_characterization-2021.2.4.dist-info/METADATA
frc_characterization-2021.2.4.dist-info/WHEEL
frc_characterization-2021.2.4.dist-info/entry_points.txt
frc_characterization-2021.2.4.dist-info/top_level.txt
frc_characterization-2021.2.4.dist-info/RECORD
