Metadata-Version: 2.1
Name: frc-characterization
Version: 2021.2.4
Summary: FRC Characterization Library
Home-page: https://github.com/wpilibsuite/robot-characterization
Author: Eli Barnett, Dustin Spicuzza
Author-email: emichaelbarnett@gmail.com, dustin@virtualroadside.com
License: UNKNOWN
Platform: UNKNOWN
Classifier: Programming Language :: Python :: 3
Classifier: License :: OSI Approved :: Apache Software License
Classifier: Operating System :: OS Independent
Requires-Python: >=3.7
Requires-Dist: control
Requires-Dist: frccontrol
Requires-Dist: matplotlib
Requires-Dist: pynetworktables (>=2018.1.2)
Requires-Dist: statsmodels
Requires-Dist: argcomplete
Requires-Dist: console-menu
Requires-Dist: mako
Requires-Dist: pint
Requires-Dist: numpy (==1.19.3) ; platform_system == "Windows"
